AUTHORS
HISTORY.rst
LICENSE
MANIFEST.in
NOTICE
README.rst
setup.py
pychievements/__init__.py
pychievements/achievements.py
pychievements/backends.py
pychievements/cli.py
pychievements/icons.py
pychievements/signals.py
pychievements/trackers.py
pychievements.egg-info/PKG-INFO
pychievements.egg-info/SOURCES.txt
pychievements.egg-info/dependency_links.txt
pychievements.egg-info/requires.txt
pychievements.egg-info/top_level.txt