Metadata-Version: 1.1
Name: pychievements
Version: 0.1.2
Summary: Python Achievements Framework
Home-page: https://github.com/PacketPerception/pychievements
Author: Brian Knobbs
Author-email: brian@packetperception.org
License: MIT
Platform: UNKNOWN
Classifier: Development Status :: 4 - Beta
Classifier: Intended Audience :: Developers
Classifier: Natural Language :: English
Classifier: License :: OSI Approved :: MIT License
Classifier: Programming Language :: Python
Classifier: Programming Language :: Python :: 2
Classifier: Programming Language :: Python :: 3
Classifier: Topic :: Software Development :: Libraries
Classifier: Topic :: Software Development :: Libraries :: Application Frameworks
